testing_some_package/__init__.py
testing_some_package/test.py
testing_some_package-0.5.10.dist-info/METADATA
testing_some_package-0.5.10.dist-info/WHEEL
testing_some_package-0.5.10.dist-info/entry_points.txt
testing_some_package-0.5.10.dist-info/RECORD
