Metadata-Version: 2.1
Name: testing-some-package
Version: 0.5.10
Summary: This is a testing package description.
Home-page: https://example.com/home
License: MIT
Keywords: AI,security,code analysis,CI/CD,GitHub
Author: addepar-tg
Author-email: thomas.greenwood@addepar.com
Requires-Python: >=3.12,<4.0
Classifier: Environment :: Console
Classifier: Environment :: Web Environment
Classifier: Intended Audience :: Developers
Classifier: Intended Audience :: Information Technology
Classifier: Intended Audience :: System Administrators
Classifier: License :: OSI Approved :: MIT License
Classifier: Natural Language :: English
Classifier: Operating System :: OS Independent
Classifier: Programming Language :: Python
Classifier: Programming Language :: Python :: 3
Classifier: Programming Language :: Python :: 3.12
Classifier: Topic :: Security
Classifier: Topic :: Software Development :: Libraries :: Python Modules
Classifier: Topic :: Software Development :: Quality Assurance
Requires-Dist: langchain (>=0.2.4,<0.3.0)
Requires-Dist: requests (>=2.32.3,<3.0.0)
Project-URL: Documentation, https://example.com/docs
Project-URL: Repository, https://github.com/Example/example-repo.git
